Metadata-Version: 1.0
Name: td-dbf2csv
Version: 1.7
Summary: Small utility to convert simple *.DBF files to *.CSV
Home-page: https://github.com/calebdinsmore/td_dbf2csv
Author: UNKNOWN
Author-email: UNKNOWN
License: UNKNOWN
Platform: any
